gogoweb/__init__.py
gogoweb/_version.py
gogoweb/convert.py
gogoweb/utils.py
gogoweb-1.0.3.dist-info/LICENSE.md
gogoweb-1.0.3.dist-info/METADATA
gogoweb-1.0.3.dist-info/WHEEL
gogoweb-1.0.3.dist-info/top_level.txt
gogoweb-1.0.3.dist-info/RECORD
