Metadata-Version: 2.1
Name: gogoweb
Version: 1.0.3
Summary: Command-line tool that converts .txt or .md files into .html files.
Home-page: https://github.com/kliu57/go-go-web
Author: Katie Liu
Author-email: Katie Liu <liu_katie@outlook.com>
Project-URL: Homepage, https://github.com/kliu57/go-go-web
Project-URL: Issues, https://github.com/kliu57/go-go-web/issues
Classifier: License :: OSI Approved :: MIT License
Requires-Python: >=3.7
License-File: LICENSE.md
Requires-Dist: tomlkit
Requires-Dist: python-frontmatter
